{
  "gitSyncId": "677bf5408959e507b80f055e_fbc1979a-ce83-46b9-98f6-9df3d9dd512f",
  "id": "devices_findAllDevices",
  "pluginId": "postgres-plugin",
  "pluginType": "DB",
  "unpublishedAction": {
    "actionConfiguration": {
      "body": "SELECT d.*, udr.owner_id, udr.display_name, udr.info\nFROM devices as d left outer JOIN user_device_relations as udr \n    ON d.serial = udr.serial and udr.delete_flag = false \nWHERE d.type_id not in (1,2);",
      "encodeParamsToggle": true,
      "paginationType": "NONE",
      "pluginSpecifiedTemplates": [
        {
          "value": false
        }
      ],
      "timeoutInMillisecond": 10000
    },
    "confirmBeforeExecute": false,
    "datasource": {
      "id": "本地数据库",
      "isAutoGenerated": false,
      "name": "本地数据库",
      "pluginId": "postgres-plugin"
    },
    "dynamicBindingPathList": [],
    "executeOnLoad": true,
    "name": "findAllDevices",
    "pageId": "devices",
    "userSetOnLoad": false
  }
}